README.md
setup.py
splitnjoin/__init__.py
splitnjoin/file_processing.py
splitnjoin/snj_benchmark.py
splitnjoin.egg-info/PKG-INFO
splitnjoin.egg-info/SOURCES.txt
splitnjoin.egg-info/dependency_links.txt
splitnjoin.egg-info/not-zip-safe
splitnjoin.egg-info/top_level.txt