Metadata-Version: 1.0
Name: splitnjoin
Version: 0.76
Summary: Simple module for splitting binary files into multiple chunks/parts and viceversa (from chunks/parts to original file)
Home-page: https://github.com/SergioLaRosa/splitnjoin
Author: Sergio La Rosa
Author-email: sergio.larosa89@gmail.com
License: MIT
Platform: UNKNOWN
